neongrid/__init__.py
neongrid/_confirm.py
neongrid/_input.py
neongrid/_print.py
neongrid/loading.py
neongrid/measure.py
neongrid/style.py
neongrid/stream/__init__.py
neongrid/stream/md/__init__.py
neongrid/stream/md/inline_text.py
neongrid/stream/md/printer.py
neongrid/stream/md/stream.py
neongrid-0.0.3.dist-info/METADATA
neongrid-0.0.3.dist-info/WHEEL
neongrid-0.0.3.dist-info/RECORD
