Metadata-Version: 2.4
Name: neongrid
Version: 0.0.3
Summary: Add your description here
Requires-Python: >=3.12
Requires-Dist: asyncio>=3.4.3
Requires-Dist: prompt-toolkit>=3.0.51
Requires-Dist: python-dotenv>=1.1.0
Requires-Dist: rich>=14.0.0
